llama_index/multi_modal_llms/gemini/__init__.py
llama_index/multi_modal_llms/gemini/base.py
llama_index/multi_modal_llms/gemini/utils.py
llama_index_multi_modal_llms_gemini-0.6.1.dist-info/METADATA
llama_index_multi_modal_llms_gemini-0.6.1.dist-info/WHEEL
llama_index_multi_modal_llms_gemini-0.6.1.dist-info/licenses/LICENSE
llama_index_multi_modal_llms_gemini-0.6.1.dist-info/RECORD
