Metadata-Version: 2.4
Name: llama-index-multi-modal-llms-gemini
Version: 0.6.1
Summary: llama-index multi-modal-llms gemini integration
Author-email: Your Name <you@example.com>
License-Expression: MIT
License-File: LICENSE
Requires-Python: <4.0,>=3.9
Requires-Dist: llama-index-core<0.15,>=0.13.0
Requires-Dist: llama-index-llms-gemini<0.7,>=0.6
Requires-Dist: pillow<11,>=10.2.0
